n8scripts/__init__.py
n8scripts/internet_on.py
n8scripts/n8markdown.py
n8scripts/n8pushover.py
n8scripts-0.1.0.dist-info/DESCRIPTION.rst
n8scripts-0.1.0.dist-info/METADATA
n8scripts-0.1.0.dist-info/RECORD
n8scripts-0.1.0.dist-info/WHEEL
n8scripts-0.1.0.dist-info/entry_points.txt
n8scripts-0.1.0.dist-info/metadata.json
n8scripts-0.1.0.dist-info/top_level.txt
