Metadata-Version: 2.0
Name: n8scripts
Version: 0.1.0
Summary: Nate's handy scripts
Home-page: https://github.com/n8henrie/n8scripts
Author: Nathan Henrie
Author-email: nate@n8henrie.com
License: MIT
Platform: UNKNOWN
Classifier: Natural Language :: English
Classifier: Programming Language :: Python :: 3
Classifier: Programming Language :: Python :: 3.6
